wizardry/__init__.py
wizardry/cli.py
wizardry-0.1.2.dist-info/entry_points.txt
wizardry-0.1.2.dist-info/WHEEL
wizardry-0.1.2.dist-info/METADATA
wizardry-0.1.2.dist-info/RECORD
